[
  {
    "id": 12781439,
    "application_id": 790,
    "name": "Alex Eveleigh",
    "first_name": "Alex",
    "last_name": "Eveleigh",
    "headline": "StrongPoint - VusionGroup",
    "summary": null,
    "job_title": "StrongPoint",
    "company_name": "VusionGroup"
  },
  {
    "id": 9537386,
    "application_id": 790,
    "name": "Alex Font Ibañez",
    "first_name": "Alex",
    "last_name": "Font Ibañez",
    "headline": "Intralogistics Business Manager - PAL Robotics S.L.",
    "summary": "",
    "job_title": "Intralogistics Business Manager",
    "company_name": "PAL Robotics S.L."
  },
  {
    "id": 15824673,
    "application_id": 790,
    "name": "ALEX FRAGA",
    "first_name": "ALEX",
    "last_name": "FRAGA",
    "headline": "VENDAS - V.S.O.P COMERCIO DE ALIMENTOS E BEBIDAS",
    "summary": null,
    "job_title": "VENDAS",
    "company_name": "V.S.O.P COMERCIO DE ALIMENTOS E BEBIDAS"
  },
  {
    "id": 12546367,
    "application_id": 790,
    "name": "Alex Frederick",
    "first_name": "Alex",
    "last_name": "Frederick",
    "headline": "Regional Retail Vice President, Sales - Toast",
    "summary": null,
    "job_title": "Regional Retail Vice President, Sales",
    "company_name": "Toast"
  },
  {
    "id": 15672221,
    "application_id": 790,
    "name": "Alex Galewsky",
    "first_name": "Alex",
    "last_name": "Galewsky",
    "headline": "GPJ - Kyndryl, Inc.",
    "summary": null,
    "job_title": "GPJ",
    "company_name": "Kyndryl, Inc."
  },
  {
    "id": 15243658,
    "application_id": 790,
    "name": "Alex Garcia",
    "first_name": "Alex",
    "last_name": "Garcia",
    "headline": "Product Manager - End Point, Cloud UPS and Power Conversion - Eaton",
    "summary": null,
    "job_title": "Product Manager - End Point, Cloud UPS and Power Conversion",
    "company_name": "Eaton"
  },
  {
    "id": 15393611,
    "application_id": 790,
    "name": "Alex Garcia",
    "first_name": "Alex",
    "last_name": "Garcia",
    "headline": "Industry Advisor - Microsoft Corporation",
    "summary": null,
    "job_title": "Industry Advisor",
    "company_name": "Microsoft Corporation"
  },
  {
    "id": 9898465,
    "application_id": 790,
    "name": "Alex Gavrilov",
    "first_name": "Alex",
    "last_name": "Gavrilov",
    "headline": "CEO - Zello",
    "summary": "",
    "job_title": "CEO",
    "company_name": "Zello"
  },
  {
    "id": 15765903,
    "application_id": 790,
    "name": "Alex Gibson",
    "first_name": "Alex",
    "last_name": "Gibson",
    "headline": "Program Manager (PgM), Cross-Meta Programs - Meta Platforms, Inc.",
    "summary": null,
    "job_title": "Program Manager (PgM), Cross-Meta Programs",
    "company_name": "Meta Platforms, Inc."
  },
  {
    "id": 15757685,
    "application_id": 790,
    "name": "Alex Gil",
    "first_name": "Alex",
    "last_name": "Gil",
    "headline": "Director, B2B Channel Sales Strategy - Samsung Electronics America",
    "summary": null,
    "job_title": "Director, B2B Channel Sales Strategy",
    "company_name": "Samsung Electronics America"
  },
  {
    "id": 12772843,
    "application_id": 790,
    "name": "Alex Gillespie",
    "first_name": "Alex",
    "last_name": "Gillespie",
    "headline": "Director - Gillespie Manners Limited",
    "summary": "",
    "job_title": "Director",
    "company_name": "Gillespie Manners Limited"
  },
  {
    "id": 15797135,
    "application_id": 790,
    "name": "Alex Godfrey",
    "first_name": "Alex",
    "last_name": "Godfrey",
    "headline": "Global Technology Partner Marketing Lead - Stripe, Inc.",
    "summary": null,
    "job_title": "Global Technology Partner Marketing Lead",
    "company_name": "Stripe, Inc."
  },
  {
    "id": 15821524,
    "application_id": 790,
    "name": "Alex Goldelman",
    "first_name": "Alex",
    "last_name": "Goldelman",
    "headline": "CFO - UNIQLO USA",
    "summary": null,
    "job_title": "CFO",
    "company_name": "UNIQLO USA"
  },
  {
    "id": 13961716,
    "application_id": 790,
    "name": "Alex Goncalves",
    "first_name": "Alex",
    "last_name": "Goncalves",
    "headline": "OPERATIONS MANAGER CORPORATE - Ancar Ivanhoe Administradora de Shopping Center LT",
    "summary": null,
    "job_title": "OPERATIONS MANAGER CORPORATE",
    "company_name": "Ancar Ivanhoe Administradora de Shopping Center LT"
  },
  {
    "id": 12450675,
    "application_id": 790,
    "name": "Alex Gongye",
    "first_name": "Alex",
    "last_name": "Gongye",
    "headline": "Solution Engineer - SUNMI Technology",
    "summary": null,
    "job_title": "Solution Engineer",
    "company_name": "SUNMI Technology"
  },
  {
    "id": 12109404,
    "application_id": 790,
    "name": "Alex Gorman",
    "first_name": "Alex",
    "last_name": "Gorman",
    "headline": "VP, eCommerce & Digital Experience - Scholastic Inc",
    "summary": null,
    "job_title": "VP, eCommerce & Digital Experience",
    "company_name": "Scholastic Inc"
  },
  {
    "linkedinAccount": "https://www.linkedin.com/in/alex-gray-7b3324b",
    "id": 9964141,
    "application_id": 790,
    "name": "Alex Gray",
    "first_name": "Alex",
    "last_name": "Gray",
    "headline": "Sr Manager Method Improvements - Ross Stores, Inc.",
    "summary": null,
    "job_title": "Sr Manager Method Improvements",
    "company_name": "Ross Stores, Inc."
  }
]